{"gamecode": "FK7X6TXM", "board": [["STRIKE", "blue", false], ["APPLE", "#2d3436", false], ["SPELL", "red", false], ["MATCH", "red", false], ["WASHINGTON", "red", false], ["RULER", "blue", false], ["BERRY", "#8B9FB3", false], ["MAMMOTH", "#8B9FB3", false], ["HEAD", "blue", false], ["KING", "#8B9FB3", false], ["KID", "#8B9FB3", false], ["SMUGGLER", "#8B9FB3", false], ["LONDON", "blue", false], ["SPOT", "red", false], ["CONCERT", "blue", false], ["NURSE", "#8B9FB3", false], ["DEGREE", "blue", false], ["BOLT", "#8B9FB3", false], ["SPY", "red", false], ["CHANGE", "blue", false], ["STICK", "blue", false], ["PIT", "red", false], ["STAFF", "red", false], ["STRING", "blue", false], ["BAT", "red", false]], "current_color": "blue", "resterende_tegels_red": 8, "resterende_tegels_blue": 9, "winner": null}