{"gamecode": "ITAH0KKO", "board": [["BEAT", "blue", false], ["SOLDIER", "blue", false], ["IRON", "blue", false], ["BRIDGE", "blue", false], ["CARROT", "blue", false], ["CONTRACT", "blue", false], ["WITCH", "blue", false], ["FILM", "blue", false], ["CHINA", "blue", false], ["BEAR", "red", false], ["SOLDIER", "red", false], ["PIPE", "red", false], ["NURSE", "red", false], ["WAKE", "red", false], ["NUT", "red", false], ["KETCHUP", "red", false], ["ENGINE", "red", false], ["PIPE", "#8B9FB3", false], ["STATE", "#8B9FB3", false], ["MOSCOW", "#8B9FB3", false], ["NEW YORK", "#8B9FB3", false], ["LION", "#8B9FB3", false], ["AMERICA", "#8B9FB3", false], ["LEMON", "#8B9FB3", false], ["FORCE", "#2d3436", false]], "current_color": "blue", "resterende_tegels_red": 8, "resterende_tegels_blue": 9, "winner": null}