{"gamecode": "PZDM6TAI", "board": [["TABLET", "blue", false], ["YARD", "red", true], ["MASS", "red", true], ["JACK", "red", true], ["COTTON", "red", false], ["POISON", "#8B9FB3", true], ["JET", "red", true], ["EYE", "red", true], ["DOCTOR", "red", false], ["COOK", "blue", true], ["THEATER", "#8B9FB3", true], ["BUGLE", "blue", true], ["CAT", "#8B9FB3", true], ["ORANGE", "#8B9FB3", true], ["COMPOUND", "#8B9FB3", false], ["VACUUM", "blue", false], ["BOND", "blue", false], ["BELL", "#8B9FB3", false], ["FALL", "#2d3436", false], ["SUPERHERO", "red", false], ["PENGUIN", "blue", false], ["FLY", "blue", false], ["ALIEN", "#8B9FB3", false], ["LONDON", "blue", false], ["DEATH", "red", false]], "current_color": "red", "resterende_tegels_red": 4, "resterende_tegels_blue": 6, "winner": null}