{"gamecode": "YJVZE9XG", "board": [["SCALE", "blue", false], ["FAIR", "red", false], ["NET", "red", false], ["WAKE", "#2d3436", false], ["HAND", "#8B9FB3", false], ["TRAIN", "#8B9FB3", false], ["WAR", "red", false], ["QUEEN", "red", false], ["SOUND", "blue", false], ["FIELD", "#8B9FB3", false], ["RAY", "blue", false], ["TRACK", "red", false], ["COOK", "blue", false], ["JUPITER", "blue", false], ["BOARD", "blue", false], ["EAGLE", "#8B9FB3", false], ["SHOT", "red", false], ["WHIP", "#8B9FB3", false], ["LEMON", "blue", false], ["PUMPKIN", "blue", false], ["MINT", "blue", false], ["HORSE", "#8B9FB3", false], ["CONCERT", "#8B9FB3", false], ["CLIFF", "red", false], ["LEMON", "red", false]], "current_color": "blue", "resterende_tegels_red": 8, "resterende_tegels_blue": 9, "winner": null}